{"uR5R4VkdqB4WB71KHy9ZfQ==":"front%20page-2000x2308.jpg","FKAW8xIRMPL/ZVRmcYJUvg==":"st%20quentin%201-2000x2640.jpg","0Xidqr5BTNA+FhTKlfjesA==":"st%20quentin%205-2000x1488.jpg","Bb7TEIPmgnMT47poD6j2aA==":"st%20quentin%204-2000x1516.jpg","WEmfV4UJ4G4bxSwrj9ECeg==":"st%20quentin%202-2000x1505.jpg","VH8hAs/LaPxJagBnpDiXiQ==":"st%20quentin%203-2000x1511.jpg","/ZNm4JmyYzd6uBzvF29d4Q==":"img-2000x1367.jpg","oD64QKmiywSvq0a6Rt73bQ==":"img-2000x1500.jpg","yZLpMBCevGRQdX3sMgsyoQ==":"img-1-2000x1500.jpg","KWh0LxbtuVuaJFCdW6/Y2w==":"img-2-2000x1500.jpg","RxwfrhjlOODMLTX+sQ3p9g==":"img-3-2000x1500.jpg","S1lPHmWCltnsjo6OlcFtMw==":"img-4-2000x1500.jpg","TxKvM5A8FpQBx/zqbFR2Fg==":"img-5-2000x1500.jpg","sW3fDzRzgjAiuCJOHPIF7w==":"mbr-2000x1333.jpg","jB3Ylx7x1Plsr0mNgsq31w==":"img-2000x4686.jpg","xEkcOUKp6F5CbjVaq9b7vg==":"fond%20ecan-2000x853.jpg","l3roUMHuPaZ3xlObqlHt8Q==":"img-6-2000x1500.jpg","AJMNYgsjJYBk12yWJEkUqQ==":"st-quentin-1-2000x2640-800x1056.jpg","bGKYAP2LjC3mudyBeX69bA==":"front%20page-1400x1615.jpg","Kzs3Zy4l6ImVEWR8GORQGg==":"img-7-2000x1500.jpg"}